js_liner/__init__.py
js_liner/test.py
js_liner-0.1.0.dist-info/METADATA
js_liner-0.1.0.dist-info/WHEEL
js_liner-0.1.0.dist-info/top_level.txt
js_liner-0.1.0.dist-info/RECORD
